MANIFEST.in
requirements-test.txt
requirements.txt
setup.py
action_optimizer/__init__.py
action_optimizer/__init__.pyc
action_optimizer/optimizer.py
action_optimizer/tests.py
action_optimizer.egg-info/PKG-INFO
action_optimizer.egg-info/SOURCES.txt
action_optimizer.egg-info/dependency_links.txt
action_optimizer.egg-info/not-zip-safe
action_optimizer.egg-info/requires.txt
action_optimizer.egg-info/top_level.txt
action_optimizer/__pycache__/__init__.cpython-35.pyc
action_optimizer/__pycache__/optimizer.cpython-35.pyc
action_optimizer/__pycache__/optimizer.cpython-36.pyc
action_optimizer/fixtures/.gitignore
action_optimizer/fixtures/test-trend.arff
action_optimizer/fixtures/test-trend.ods