Metadata-Version: 1.1
Name: action-optimizer
Version: 0.8.0
Summary: A tool for analyzing sequence metrics to find an optimal daily routine.
Home-page: https://github.com/chrisspen/action-optimizer
Author: Chris Spencer
Author-email: chrisspen@gmail.com
License: BSD
Platform: UNKNOWN
Classifier: Development Status :: 3 - Alpha
Classifier: License :: OSI Approved :: BSD License
Classifier: Operating System :: OS Independent
Classifier: Programming Language :: Python
Classifier: Programming Language :: Python :: 3.6
Classifier: Framework :: Django
